alation_ai_agent_mcp-0.12.0.dist-info/METADATA
alation_ai_agent_mcp-0.12.0.dist-info/WHEEL
alation_ai_agent_mcp-0.12.0.dist-info/entry_points.txt
alation_ai_agent_mcp-0.12.0.dist-info/licenses/LICENSE
alation_ai_agent_mcp/__init__.py
alation_ai_agent_mcp/__main__.py
alation_ai_agent_mcp/auth.py
alation_ai_agent_mcp/register_tools.py
alation_ai_agent_mcp/server.py
alation_ai_agent_mcp/utils.py
alation_ai_agent_mcp-0.12.0.dist-info/RECORD
