Metadata-Version: 2.1
Name: alation-ai-agent-mcp
Version: 0.12.0
Summary: Alation Agent SDK with MCP support
Keywords: Alation,AI Agent SDK,Alation Agent Python SDK,Alation AI Agent SDK
Author-Email: "Jagannath (Jags) Saragadam" <jags.saragadam@alation.com>, Lucy Eun <lucy.eun@alation.com>, Ashwin Kumar Muruganandam <ashwin-kumar.muruganandam@alation.com>, Adam Talmadge <adam.talmadge@alation.com>
Maintainer-Email: "Jagannath (Jags) Saragadam" <jags.saragadam@alation.com>, Lucy Eun <lucy.eun@alation.com>, Ashwin Kumar Muruganandam <ashwin-kumar.muruganandam@alation.com>, Adam Talmadge <adam.talmadge@alation.com>
License:                                  Apache License
Classifier: Programming Language :: Python :: 3
Classifier: Operating System :: OS Independent
Classifier: License :: OSI Approved :: Apache Software License
Project-URL: Homepage, https://github.com/Alation/alation-ai-agent-sdk/tree/main/python/dist-mcp
Project-URL: Issues, https://github.com/Alation/alation-ai-agent-sdk/issues
Project-URL: Documentation, https://github.com/Alation/alation-ai-agent-sdk/blob/main/python/dist-mcp/README.md
Requires-Python: >=3.10
Requires-Dist: alation-ai-agent-sdk>=0.12.0
Requires-Dist: mcp[cli]>=1.12.0
Requires-Dist: fastMCP==2.9.0
Requires-Dist: pydantic<2.12.0,>=2.8.0
Provides-Extra: dev
Requires-Dist: pytest>=8.3.5; extra == "dev"
Requires-Dist: ruff>=0.11.8; extra == "dev"
